cryptoString/__init__.py
cryptoString-1.0.0.dist-info/METADATA
cryptoString-1.0.0.dist-info/WHEEL
cryptoString-1.0.0.dist-info/entry_points.txt
cryptoString-1.0.0.dist-info/top_level.txt
cryptoString-1.0.0.dist-info/RECORD
