Metadata-Version: 2.1
Name: cryptoString
Version: 1.0.0
Summary: A module that returns alphanumeric strings.
Home-page: https://github.com/1010code/cryptoString
Author: andy6804tw
Author-email: andy6804tw@yahoo.com.tw
License: UNKNOWN
Platform: UNKNOWN
